.gitignore
.gitlab-ci.yml
.readthedocs.yml
COPYING.md
FILESTRUCTURE.md
LICENSE.md
README.md
TODO.md
codecov.yml
pre-commit-config.yml
pypi.yml
pyproject.toml
setup.py
.github/dependabot.yml
.github/workflows/ci.yml
.github/workflows/pypi.yml
SSC_example/__init__.py
SSC_example.egg-info/PKG-INFO
SSC_example.egg-info/SOURCES.txt
SSC_example.egg-info/dependency_links.txt
SSC_example.egg-info/requires.txt
SSC_example.egg-info/top_level.txt
doc/Makefile
doc/api.rst
doc/conf.py
doc/demo.nblink
doc/index.rst
doc/intro.rst
doc/make.bat
notebooks/demo.ipynb
tests/__init__.py
tests/conftest.py
tests/test_SSC_example.py